library3D/__init__.py
library3D/core.py
library3D/graphics.py
library3D/math3d.py
library3d-0.25.dist-info/METADATA
library3d-0.25.dist-info/WHEEL
library3d-0.25.dist-info/top_level.txt
library3d-0.25.dist-info/RECORD
