Metadata-Version: 2.4
Name: library3d
Version: 0.25
Summary: Saf Python 3D kütüphanesi (OpenGL kullanmadan, v0.25)
Home-page: https://github.com/kullaniciadi/library3d
Author: Mehmet
Classifier: Programming Language :: Python :: 3
Classifier: License :: OSI Approved :: MIT License
Classifier: Operating System :: OS Independent
Requires-Python: >=3.7
Requires-Dist: Pillow
Dynamic: author
Dynamic: classifier
Dynamic: description
Dynamic: description-content-type
Dynamic: home-page
Dynamic: requires-dist
Dynamic: requires-python
Dynamic: summary
